workrb/__init__.py
workrb/config.py
workrb/logging.py
workrb/registry.py
workrb/results.py
workrb/run.py
workrb/types.py
workrb/data/__init__.py
workrb/data/esco.py
workrb/metrics/__init__.py
workrb/metrics/classification.py
workrb/metrics/ranking.py
workrb/metrics/reporting.py
workrb/models/__init__.py
workrb/models/base.py
workrb/models/bi_encoder.py
workrb/models/classification_model.py
workrb/models/curriculum_encoder.py
workrb/tasks/__init__.py
workrb/tasks/abstract/__init__.py
workrb/tasks/abstract/base.py
workrb/tasks/abstract/classification_base.py
workrb/tasks/abstract/ranking_base.py
workrb/tasks/classification/__init__.py
workrb/tasks/classification/job2skill.py
workrb/tasks/ranking/__init__.py
workrb/tasks/ranking/job2skill.py
workrb/tasks/ranking/job_similarity.py
workrb/tasks/ranking/jobnorm.py
workrb/tasks/ranking/skill2job.py
workrb/tasks/ranking/skill_extraction.py
workrb/tasks/ranking/skill_similarity.py
workrb/tasks/ranking/skillnorm.py
workrb-0.3.0.dist-info/METADATA
workrb-0.3.0.dist-info/WHEEL
workrb-0.3.0.dist-info/licenses/LICENSE
workrb-0.3.0.dist-info/licenses/NOTICE
workrb-0.3.0.dist-info/RECORD
