Metadata-Version: 2.4
Name: workrb
Version: 0.3.0
Summary: WorkRB: Work Research Benchmark. Easy benchmarking of AI progress in the work domain.
Project-URL: Homepage, https://github.com/techwolf-ai/workrb
Project-URL: Documentation, https://github.com/techwolf-ai/workrb#readme
Project-URL: Repository, https://github.com/techwolf-ai/workrb.git
Project-URL: Issues, https://github.com/techwolf-ai/workrb/issues
Author: TechWolf Research Team
Author-email: Matthias De Lange <matthias.delange@techwolf.ai>
License: Apache 2.0
License-File: LICENSE
License-File: NOTICE
Keywords: benchmarking,evaluation,jobs,machine-learning,nlp,skills
Classifier: Intended Audience :: Developers
Classifier: Intended Audience :: Science/Research
Classifier: License :: OSI Approved :: Apache Software License
Classifier: Operating System :: OS Independent
Classifier: Programming Language :: Python :: 3
Classifier: Topic :: Scientific/Engineering :: Artificial Intelligence
Classifier: Topic :: Text Processing :: Linguistic
Requires-Python: <4.0,>=3.10
Requires-Dist: appdirs>=1.4.4
Requires-Dist: datasets>=2.18.0
Requires-Dist: numpy>=1.24.0
Requires-Dist: pandas>=2.0.0
Requires-Dist: pydantic>=2.11.9
Requires-Dist: pyyaml>=6.0
Requires-Dist: requests>=2.31.0
Requires-Dist: scikit-learn>=1.6.1
Requires-Dist: sentence-transformers>=5.1.0
Requires-Dist: torch>=2.6.0
Requires-Dist: tqdm>=4.65.0
